[
{"type":"header","version":"5.2.1","comment":"Export to JSON plugin for PHPMyAdmin"},
{"type":"database","name":"amd-db"},
{"type":"table","name":"app_master_relation","database":"amd-db","data":
[
{"id":"1","title":"पिता - पुत्र","status":"1","created_at":"2026-06-15 20:02:02","updated_at":"2026-06-16 01:32:02","created_by":"0"},
{"id":"2","title":"पिता-पुत्री","status":"1","created_at":"2025-06-25 14:55:59","updated_at":"2025-06-25 20:25:59","created_by":"0"},
{"id":"3","title":"मामा-भोणेज","status":"1","created_at":"2025-06-25 14:49:17","updated_at":"2025-06-25 20:19:17","created_by":"0"},
{"id":"4","title":"माता-पुत्र","status":"1","created_at":"2025-06-25 14:49:45","updated_at":"2025-06-25 20:19:45","created_by":"0"},
{"id":"5","title":"माता-पुत्री","status":"1","created_at":"2025-06-25 14:50:21","updated_at":"2025-06-25 20:20:21","created_by":"1"},
{"id":"6","title":"मामा-भान्जी","status":"1","created_at":"2025-06-25 14:50:57","updated_at":"2025-06-25 20:20:57","created_by":"1"},
{"id":"7","title":"दादी-पोता","status":"1","created_at":"2025-09-11 07:09:34","updated_at":"2025-09-11 12:39:34","created_by":"1"},
{"id":"8","title":"दादा","status":"1","created_at":"2025-06-25 14:51:48","updated_at":"2025-06-25 20:21:48","created_by":"1"},
{"id":"9","title":"मोमी-भोणेज","status":"1","created_at":"2025-06-25 14:52:16","updated_at":"2025-06-25 20:22:16","created_by":"1"},
{"id":"10","title":"मोमी-भोणेजी","status":"1","created_at":"2025-06-25 14:52:59","updated_at":"2025-06-25 20:22:59","created_by":"1"},
{"id":"11","title":"पति-पत्नी","status":"1","created_at":"2025-06-25 14:54:15","updated_at":"2025-06-25 20:24:15","created_by":"1"},
{"id":"12","title":"भाई-बहिन","status":"1","created_at":"2025-06-25 14:54:47","updated_at":"2025-06-25 20:24:47","created_by":"1"},
{"id":"13","title":"अन्य","status":"1","created_at":"2026-06-29 19:20:54","updated_at":"2026-06-30 00:50:54","created_by":"1"},
{"id":"14","title":"बहिन","status":"1","created_at":"2025-06-25 14:54:59","updated_at":"2025-06-25 20:24:59","created_by":"1"},
{"id":"15","title":"भुआ-भतिजी","status":"1","created_at":"2025-06-25 14:55:36","updated_at":"2025-06-25 20:25:36","created_by":"1"},
{"id":"16","title":"काका-भतिजा","status":"1","created_at":"2025-11-16 19:58:37","updated_at":"2025-11-17 01:28:37","created_by":"1"},
{"id":"17","title":"काका-भतिजी","status":"1","created_at":"2025-06-26 13:33:52","updated_at":"2025-06-26 13:33:52","created_by":"1"},
{"id":"18","title":"भाई","status":"1","created_at":"2025-09-17 02:17:46","updated_at":"2025-09-17 02:17:46","created_by":"1"},
{"id":"19","title":"नानी","status":"1","created_at":"2025-11-08 11:53:45","updated_at":"2025-11-08 17:23:45","created_by":"1"},
{"id":"20","title":"नाना","status":"1","created_at":"2025-11-04 20:54:36","updated_at":"2025-11-04 20:54:36","created_by":"1"},
{"id":"21","title":"जमाई","status":"1","created_at":"2026-04-02 03:04:39","updated_at":"2026-04-02 03:04:39","created_by":"1"},
{"id":"22","title":"पुत्र वधू - ससुर","status":"1","created_at":"2026-06-27 00:28:44","updated_at":"2026-06-27 00:28:44","created_by":"0"},
{"id":"23","title":"दादा-पोता","status":"1","created_at":"2026-06-29 23:41:26","updated_at":"2026-06-29 23:41:26","created_by":"0"}
]
}
]
